{"type":"PR","pr":{"number":25,"head":"38ba903c7d501a07236814c16e217531cbc2dc33"},"user":"the2deux","status":"draft","branch":"cms/2018-10-22-6-raisons-d-avoir-une-boutique-en-ligne-en-2018","collection":"articles-fr","title":"6 raisons d'avoir une boutique en ligne en 2018","description":"On ne sera pas les premiers à vous le dire: si votre entreprise n'a pas de boutique en ligne en 2018, vous manquez le bateau. Découvrez comment une boutique en ligne pourrait augmenter vos ventes, mais aussi la fidelité de vos clients","objects":{"entry":{"path":"content/articles/2018-10-22-6-raisons-d-avoir-une-boutique-en-ligne-en-2018.md","sha":"1640ce4185ca0cdf20ce29b05b7669da78f76022"},"files":[]},"timeStamp":"2018-10-22T16:48:04.982Z"}